{
  "main": {
    "id": "845759493d58b964",
    "type": "split",
    "children": [
      {
        "id": "fa8cf55608ab7563",
        "type": "tabs",
        "children": [
          {
            "id": "ca83422591afb5ee",
            "type": "leaf",
            "state": {
              "type": "markdown",
              "state": {
                "file": "test/2025-07-26.md",
                "mode": "source",
                "source": false
              },
              "icon": "lucide-file",
              "title": "2025-07-26"
            }
          }
        ]
      }
    ],
    "direction": "vertical"
  },
  "left": {
    "id": "7826e03b6bb180ce",
    "type": "mobile-drawer",
    "children": [
      {
        "id": "5ff3baab30c14644",
        "type": "leaf",
        "state": {
          "type": "file-explorer",
          "state": {
            "sortOrder": "alphabetical",
            "autoReveal": false
          },
          "icon": "lucide-folder-closed",
          "title": "Files"
        }
      },
      {
        "id": "f71773a9b79f0005",
        "type": "leaf",
        "state": {
          "type": "search",
          "state": {
            "query": "",
            "matchingCase": false,
            "explainSearch": false,
            "collapseAll": false,
            "extraContext": false,
            "sortOrder": "alphabetical"
          },
          "icon": "lucide-search",
          "title": "Search"
        }
      },
      {
        "id": "ba755434af655451",
        "type": "leaf",
        "state": {
          "type": "tag",
          "state": {
            "sortOrder": "frequency",
            "useHierarchy": true,
            "showSearch": false,
            "searchQuery": ""
          },
          "icon": "lucide-tags",
          "title": "Tags"
        }
      },
      {
        "id": "1cee0dbb51428d65",
        "type": "leaf",
        "state": {
          "type": "bookmarks",
          "state": {},
          "icon": "lucide-bookmark",
          "title": "Bookmarks"
        }
      }
    ],
    "currentTab": 0
  },
  "right": {
    "id": "927356fe8023d13d",
    "type": "mobile-drawer",
    "children": [
      {
        "id": "6a714ba6060d12d0",
        "type": "leaf",
        "state": {
          "type": "backlink",
          "state": {
            "file": "test/2025-07-26.md",
            "collapseAll": false,
            "extraContext": false,
            "sortOrder": "alphabetical",
            "showSearch": false,
            "searchQuery": "",
            "backlinkCollapsed": false,
            "unlinkedCollapsed": true
          },
          "icon": "links-coming-in",
          "title": "Backlinks"
        }
      },
      {
        "id": "a15a27e81f9795ba",
        "type": "leaf",
        "state": {
          "type": "outgoing-link",
          "state": {
            "file": "test/2025-07-26.md",
            "linksCollapsed": false,
            "unlinkedCollapsed": true
          },
          "icon": "links-going-out",
          "title": "Outgoing links"
        }
      },
      {
        "id": "21028fbca478549e",
        "type": "leaf",
        "state": {
          "type": "outline",
          "state": {
            "file": "test/2025-07-26.md",
            "followCursor": false,
            "showSearch": false,
            "searchQuery": ""
          },
          "icon": "lucide-list",
          "title": "Outline"
        }
      }
    ],
    "currentTab": 0
  },
  "left-ribbon": {
    "hiddenItems": {
      "switcher:Open quick switcher": false,
      "graph:Open graph view": false,
      "canvas:Create new canvas": false,
      "daily-notes:Open today's daily note": false,
      "templates:Insert template": false,
      "command-palette:Open command palette": false
    }
  },
  "active": "ca83422591afb5ee",
  "lastOpenFiles": []
}